odoo/addons/website_js_below_the_fold/README.rst
odoo/addons/website_js_below_the_fold/__init__.py
odoo/addons/website_js_below_the_fold/__manifest__.py
odoo/addons/website_js_below_the_fold/templates/website_js_below_the_fold.xml
odoo11_addon_website_js_below_the_fold-11.0.1.0.0.dist-info/DESCRIPTION.rst
odoo11_addon_website_js_below_the_fold-11.0.1.0.0.dist-info/METADATA
odoo11_addon_website_js_below_the_fold-11.0.1.0.0.dist-info/RECORD
odoo11_addon_website_js_below_the_fold-11.0.1.0.0.dist-info/WHEEL
odoo11_addon_website_js_below_the_fold-11.0.1.0.0.dist-info/metadata.json
odoo11_addon_website_js_below_the_fold-11.0.1.0.0.dist-info/top_level.txt
